huaweicloudsdkcodeartspipeline/__init__.py
huaweicloudsdkcodeartspipeline/v2/__init__.py
huaweicloudsdkcodeartspipeline/v2/codeartspipeline_async_client.py
huaweicloudsdkcodeartspipeline/v2/codeartspipeline_client.py
huaweicloudsdkcodeartspipeline/v2/model/__init__.py
huaweicloudsdkcodeartspipeline/v2/model/accept_manual_review_request.py
huaweicloudsdkcodeartspipeline/v2/model/accept_manual_review_response.py
huaweicloudsdkcodeartspipeline/v2/model/actions_manual_run_pipeline_dto.py
huaweicloudsdkcodeartspipeline/v2/model/actions_pipeline_runs_polling_query_dto.py
huaweicloudsdkcodeartspipeline/v2/model/actions_pipeline_runs_query_dto.py
huaweicloudsdkcodeartspipeline/v2/model/actions_re_run_pipeline_dto.py
huaweicloudsdkcodeartspipeline/v2/model/agent_plugin_info_query_dto.py
huaweicloudsdkcodeartspipeline/v2/model/artifact.py
huaweicloudsdkcodeartspipeline/v2/model/artifact_hash_code.py
huaweicloudsdkcodeartspipeline/v2/model/batch_move_pipeline_to_group_request.py
huaweicloudsdkcodeartspipeline/v2/model/batch_move_pipeline_to_group_response.py
huaweicloudsdkcodeartspipeline/v2/model/batch_show_pipelines_latest_status_request.py
huaweicloudsdkcodeartspipeline/v2/model/batch_show_pipelines_latest_status_response.py
huaweicloudsdkcodeartspipeline/v2/model/batch_show_pipelines_status_request.py
huaweicloudsdkcodeartspipeline/v2/model/batch_show_pipelines_status_response.py
huaweicloudsdkcodeartspipeline/v2/model/business_type_plugins_query_dto.py
huaweicloudsdkcodeartspipeline/v2/model/code_event.py
huaweicloudsdkcodeartspipeline/v2/model/code_source.py
huaweicloudsdkcodeartspipeline/v2/model/code_source_params.py
huaweicloudsdkcodeartspipeline/v2/model/constraint.py
huaweicloudsdkcodeartspipeline/v2/model/create_basic_plugin_request.py
huaweicloudsdkcodeartspipeline/v2/model/create_basic_plugin_response.py
huaweicloudsdkcodeartspipeline/v2/model/create_pipeline_by_template_id_request.py
huaweicloudsdkcodeartspipeline-3.1.184.dist-info/METADATA
huaweicloudsdkcodeartspipeline-3.1.184.dist-info/WHEEL
huaweicloudsdkcodeartspipeline-3.1.184.dist-info/licenses/LICENSE
huaweicloudsdkcodeartspipeline-3.1.184.dist-info/RECORD
